[{"name":".gitignore","path":".gitignore","size":1495},{"name":"__init__.py","path":"blog/__init__.py","size":0},{"name":"admin.py","path":"blog/admin.py","size":810},{"name":"apps.py","path":"blog/apps.py","size":83},{"name":"forms.py","path":"blog/forms.py","size":2803},{"name":"0001_initial.py","path":"blog/migrations/0001_initial.py","size":1493},{"name":"0002_auto_20210128_1148.py","path":"blog/migrations/0002_auto_20210128_1148.py","size":391},{"name":"0003_comment.py","path":"blog/migrations/0003_comment.py","size":1123},{"name":"0004_auto_20210129_1142.py","path":"blog/migrations/0004_auto_20210129_1142.py","size":386},{"name":"0005_auto_20210129_1656.py","path":"blog/migrations/0005_auto_20210129_1656.py","size":458},{"name":"0006_auto_20210129_1715.py","path":"blog/migrations/0006_auto_20210129_1715.py","size":443},{"name":"0007_auto_20210610_0610.py","path":"blog/migrations/0007_auto_20210610_0610.py","size":369},{"name":"__init__.py","path":"blog/migrations/__init__.py","size":0},{"name":"models.py","path":"blog/models.py","size":2457},{"name":"sitemaps.py","path":"blog/sitemaps.py","size":256},{"name":"__init__.py","path":"blog/templatetags/__init__.py","size":0},{"name":"blog_tags.py","path":"blog/templatetags/blog_tags.py","size":267},{"name":"tests.py","path":"blog/tests.py","size":60},{"name":"urls.py","path":"blog/urls.py","size":574},{"name":"views.py","path":"blog/views.py","size":3335},{"name":"__init__.py","path":"company/__init__.py","size":0},{"name":"asgi.py","path":"company/asgi.py","size":391},{"name":"settings.py","path":"company/settings.py","size":5517},{"name":"urls.py","path":"company/urls.py","size":1575},{"name":"wsgi.py","path":"company/wsgi.py","size":391},{"name":"manage.py","path":"manage.py","size":663},{"name":"Da5-blood.jpg","path":"media/banners/Da5-blood.jpg","size":71438},{"name":"Kim.jpg","path":"media/banners/Kim.jpg","size":46244},{"name":"about.png","path":"media/banners/about.png","size":48810},{"name":"advanced-feature-3.jpg","path":"media/banners/advanced-feature-3.jpg","size":10739},{"name":"blog-1.jpg","path":"media/banners/blog-1.jpg","size":83878},{"name":"blog-1_FP4bwji.jpg","path":"media/banners/blog-1_FP4bwji.jpg","size":83878},{"name":"blog-1_Fd4X4jB.jpg","path":"media/banners/blog-1_Fd4X4jB.jpg","size":83878},{"name":"blog-2.jpg","path":"media/banners/blog-2.jpg","size":112816},{"name":"blog-2_1pPfBqb.jpg","path":"media/banners/blog-2_1pPfBqb.jpg","size":112816},{"name":"blog-2_fdUY7k9.jpg","path":"media/banners/blog-2_fdUY7k9.jpg","size":112816},{"name":"blog-2_kI2ZF6X.jpg","path":"media/banners/blog-2_kI2ZF6X.jpg","size":112816},{"name":"blog-3.jpg","path":"media/banners/blog-3.jpg","size":93369},{"name":"blog-3_PWqlZAV.jpg","path":"media/banners/blog-3_PWqlZAV.jpg","size":93369},{"name":"blog-4.jpg","path":"media/banners/blog-4.jpg","size":104099},{"name":"blog-4_FXJkltX.jpg","path":"media/banners/blog-4_FXJkltX.jpg","size":104099},{"name":"blog-4_wW0FYvQ.jpg","path":"media/banners/blog-4_wW0FYvQ.jpg","size":104099},{"name":"blog-author.jpg","path":"media/banners/blog-author.jpg","size":64790},{"name":"castleV.jpg","path":"media/banners/castleV.jpg","size":887701},{"name":"django.png","path":"media/banners/django.png","size":121628},{"name":"love.jpg","path":"media/banners/love.jpg","size":589969},{"name":"okey.jpg","path":"media/banners/okey.jpg","size":135997},{"name":"okey_I2YSXyY.jpg","path":"media/banners/okey_I2YSXyY.jpg","size":73888},{"name":"660ec2c3-6ed1-4e8d-88e0-60e874418d50.jpg","path":"media/django-summernote/2021-06-10/660ec2c3-6ed1-4e8d-88e0-60e874418d50.jpg","size":120899},{"name":"bac76ba8-238c-47f3-b603-e52cbeff1d52.jpeg","path":"media/django-summernote/2021-06-10/bac76ba8-238c-47f3-b603-e52cbeff1d52.jpeg","size":157043},{"name":"__init__.py","path":"pages/__init__.py","size":0},{"name":"admin.py","path":"pages/admin.py","size":63},{"name":"apps.py","path":"pages/apps.py","size":85},{"name":"forms.py","path":"pages/forms.py","size":1685},{"name":"__init__.py","path":"pages/migrations/__init__.py","size":0},{"name":"models.py","path":"pages/models.py","size":57},{"name":"tests.py","path":"pages/tests.py","size":1744},{"name":"urls.py","path":"pages/urls.py","size":2450},{"name":"views.py","path":"pages/views.py","size":4299},{"name":"requirements.txt","path":"requirements.txt","size":519},{"name":"f_style.css","path":"static/assets/css/f_style.css","size":43},{"name":"froala_blocks.min.css","path":"static/assets/css/froala_blocks.min.css","size":29804},{"name":"style.css","path":"static/assets/css/style.css","size":39613},{"name":"1.svg","path":"static/assets/img/1.svg","size":1361},{"name":"10.svg","path":"static/assets/img/10.svg","size":897},{"name":"127-1272290_portable-network-graphics-hd-png-download.png.jpeg","path":"static/assets/img/127-1272290_portable-network-graphics-hd-png-download.png.jpeg","size":47322},{"name":"2.svg","path":"static/assets/img/2.svg","size":889},{"name":"4.svg","path":"static/assets/img/4.svg","size":790},{"name":"5.svg","path":"static/assets/img/5.svg","size":850},{"name":"6.svg","path":"static/assets/img/6.svg","size":602},{"name":"7.svg","path":"static/assets/img/7.svg","size":766},{"name":"8.svg","path":"static/assets/img/8.svg","size":526},{"name":"9.svg","path":"static/assets/img/9.svg","size":552},{"name":"Brand-printing.png","path":"static/assets/img/Brand-printing.png","size":10192},{"name":"Python.webp","path":"static/assets/img/Python.webp","size":19060},{"name":"about-extra-1.svg","path":"static/assets/img/about-extra-1.svg","size":19582},{"name":"about-extra-2.svg","path":"static/assets/img/about-extra-2.svg","size":76972},{"name":"about-img.png","path":"static/assets/img/about-img.png","size":61407},{"name":"about-img.svg","path":"static/assets/img/about-img.svg","size":71486},{"name":"about.jpg","path":"static/assets/img/about.jpg","size":35293},{"name":"about.png","path":"static/assets/img/about.png","size":30416},{"name":"advanced-feature-3.jpg","path":"static/assets/img/advanced-feature-3.jpg","size":10739},{"name":"angularjs-dev.webp","path":"static/assets/img/angularjs-dev.webp","size":88682},{"name":"angularjs.webp","path":"static/assets/img/angularjs.webp","size":13458},{"name":"apple-touch-icon.png","path":"static/assets/img/apple-touch-icon.png","size":1738},{"name":"banner_html.webp","path":"static/assets/img/banner_html.webp","size":12998},{"name":"blog-1.jpg","path":"static/assets/img/blog/blog-1.jpg","size":83878},{"name":"blog-2.jpg","path":"static/assets/img/blog/blog-2.jpg","size":112816},{"name":"blog-3.jpg","path":"static/assets/img/blog/blog-3.jpg","size":93369},{"name":"blog-4.jpg","path":"static/assets/img/blog/blog-4.jpg","size":104099},{"name":"blog-author.jpg","path":"static/assets/img/blog/blog-author.jpg","size":64790},{"name":"blog-inside-post.jpg","path":"static/assets/img/blog/blog-inside-post.jpg","size":85335},{"name":"blog-recent-1.jpg","path":"static/assets/img/blog/blog-recent-1.jpg","size":83411},{"name":"blog-recent-2.jpg","path":"static/assets/img/blog/blog-recent-2.jpg","size":78239},{"name":"blog-recent-3.jpg","path":"static/assets/img/blog/blog-recent-3.jpg","size":71055},{"name":"blog-recent-4.jpg","path":"static/assets/img/blog/blog-recent-4.jpg","size":115012},{"name":"blog-recent-5.jpg","path":"static/assets/img/blog/blog-recent-5.jpg","size":93369},{"name":"comments-1.jpg","path":"static/assets/img/blog/comments-1.jpg","size":17444},{"name":"comments-2.jpg","path":"static/assets/img/blog/comments-2.jpg","size":15407},{"name":"comments-3.jpg","path":"static/assets/img/blog/comments-3.jpg","size":17041},{"name":"comments-4.jpg","path":"static/assets/img/blog/comments-4.jpg","size":17774},{"name":"comments-5.jpg","path":"static/assets/img/blog/comments-5.jpg","size":10855},{"name":"comments-6.jpg","path":"static/assets/img/blog/comments-6.jpg","size":14253},{"name":"user.png","path":"static/assets/img/blog/user.png","size":21211},{"name":"blog-1.jpg","path":"static/assets/img/blog-1.jpg","size":83878},{"name":"blog-2.jpg","path":"static/assets/img/blog-2.jpg","size":112816},{"name":"blog-3.jpg","path":"static/assets/img/blog-3.jpg","size":93369},{"name":"blog-4.jpg","path":"static/assets/img/blog-4.jpg","size":104099},{"name":"browsers.svg","path":"static/assets/img/browsers.svg","size":100300},{"name":"chat.svg","path":"static/assets/img/chat.svg","size":2578},{"name":"chatting.svg","path":"static/assets/img/chatting.svg","size":11084},{"name":"content.png","path":"static/assets/img/content.png","size":9788},{"name":"cta-bg.jpg","path":"static/assets/img/cta-bg.jpg","size":172183},{"name":"customer-survey.svg","path":"static/assets/img/customer-survey.svg","size":7510},{"name":"adobe.svg","path":"static/assets/img/customers/adobe.svg","size":3148},{"name":"amazon.svg","path":"static/assets/img/customers/amazon.svg","size":6829},{"name":"apple.svg","path":"static/assets/img/customers/apple.svg","size":1244},{"name":"cisco.svg","path":"static/assets/img/customers/cisco.svg","size":4751},{"name":"discovery.svg","path":"static/assets/img/customers/discovery.svg","size":215303},{"name":"ebay.svg","path":"static/assets/img/customers/ebay.svg","size":1678},{"name":"ibm.svg","path":"static/assets/img/customers/ibm.svg","size":4450},{"name":"intel.svg","path":"static/assets/img/customers/intel.svg","size":3576},{"name":"orange.svg","path":"static/assets/img/customers/orange.svg","size":2189},{"name":"panasonic.svg","path":"static/assets/img/customers/panasonic.svg","size":5474},{"name":"salesforce.svg","path":"static/assets/img/customers/salesforce.svg","size":7363},{"name":"samsung.svg","path":"static/assets/img/customers/samsung.svg","size":2251},{"name":"design-life.svg","path":"static/assets/img/design-life.svg","size":86753},{"name":"designer.svg","path":"static/assets/img/designer.svg","size":62358},{"name":"desktop-frame-about.gif","path":"static/assets/img/desktop-frame-about.gif","size":123618},{"name":"details-1.png","path":"static/assets/img/details-1.png","size":317501},{"name":"details-2.png","path":"static/assets/img/details-2.png","size":474472},{"name":"details-3.png","path":"static/assets/img/details-3.png","size":186159},{"name":"details-4.png","path":"static/assets/img/details-4.png","size":327685},{"name":"developer.svg","path":"static/assets/img/developer.svg","size":27643},{"name":"favicon.png","path":"static/assets/img/favicon.png","size":491},{"name":"features-1.svg","path":"static/assets/img/features-1.svg","size":56848},{"name":"features-2.png","path":"static/assets/img/features-2.png","size":27363},{"name":"features-2.svg","path":"static/assets/img/features-2.svg","size":16929},{"name":"features-3.png","path":"static/assets/img/features-3.png","size":42158},{"name":"features-3.svg","path":"static/assets/img/features-3.svg","size":14533},{"name":"features-4.png","path":"static/assets/img/features-4.png","size":37662},{"name":"features-4.svg","path":"static/assets/img/features-4.svg","size":8069},{"name":"features-5.svg","path":"static/assets/img/features-5.svg","size":8432},{"name":"features.svg","path":"static/assets/img/features.svg","size":16077},{"name":"features6.svg","path":"static/assets/img/features6.svg","size":88071},{"name":"ferenc-almasi-eYpcLDXHVb0-unsplash.jpg","path":"static/assets/img/ferenc-almasi-eYpcLDXHVb0-unsplash.jpg","size":767092},{"name":"fotis-fotopoulos-DuHKoV44prg-unsplash.jpg","path":"static/assets/img/fotis-fotopoulos-DuHKoV44prg-unsplash.jpg","size":2552883},{"name":"gallery-1.jpg","path":"static/assets/img/gallery/gallery-1.jpg","size":59606},{"name":"gallery-2.jpg","path":"static/assets/img/gallery/gallery-2.jpg","size":40454},{"name":"gallery-3.jpg","path":"static/assets/img/gallery/gallery-3.jpg","size":43016},{"name":"gallery-4.jpg","path":"static/assets/img/gallery/gallery-4.jpg","size":87419},{"name":"gallery-5.jpg","path":"static/assets/img/gallery/gallery-5.jpg","size":61556},{"name":"gallery-6.jpg","path":"static/assets/img/gallery/gallery-6.jpg","size":88448},{"name":"gallery-7.jpg","path":"static/assets/img/gallery/gallery-7.jpg","size":45363},{"name":"gallery-8.jpg","path":"static/assets/img/gallery/gallery-8.jpg","size":58149},{"name":"git.svg","path":"static/assets/img/git.svg","size":19900},{"name":"hero-01.png","path":"static/assets/img/hero-01.png","size":89456},{"name":"hero-bg.jpg","path":"static/assets/img/hero-bg.jpg","size":90325},{"name":"hero-img.png","path":"static/assets/img/hero-img.png","size":25868},{"name":"hero-img10.png","path":"static/assets/img/hero-img10.png","size":11288},{"name":"hero-img2.png","path":"static/assets/img/hero-img2.png","size":71248},{"name":"hero-img3.png","path":"static/assets/img/hero-img3.png","size":239141},{"name":"hero-img4.png","path":"static/assets/img/hero-img4.png","size":25418},{"name":"hero-img5.png","path":"static/assets/img/hero-img5.png","size":49210},{"name":"hero-img6.png","path":"static/assets/img/hero-img6.png","size":34759},{"name":"hero-img7.png","path":"static/assets/img/hero-img7.png","size":52533},{"name":"hero-img8.png","path":"static/assets/img/hero-img8.png","size":77791},{"name":"hero-img9.png","path":"static/assets/img/hero-img9.png","size":148288},{"name":"hero-sw.png","path":"static/assets/img/hero-sw.png","size":124946},{"name":"img.png","path":"static/assets/img/img.png","size":31556},{"name":"img1.webp","path":"static/assets/img/img1.webp","size":24830},{"name":"img2.png","path":"static/assets/img/img2.png","size":27450},{"name":"img2.webp","path":"static/assets/img/img2.webp","size":155098},{"name":"img3.png","path":"static/assets/img/img3.png","size":162006},{"name":"img3.webp","path":"static/assets/img/img3.webp","size":58620},{"name":"img4.png","path":"static/assets/img/img4.png","size":163105},{"name":"img4.webp","path":"static/assets/img/img4.webp","size":167822},{"name":"img5.webp","path":"static/assets/img/img5.webp","size":393350},{"name":"img6.png","path":"static/assets/img/img6.png","size":157314},{"name":"img7.png","path":"static/assets/img/img7.png","size":39786},{"name":"intro-img.svg","path":"static/assets/img/intro-img.svg","size":76972},{"name":"intro-img2.svg","path":"static/assets/img/intro-img2.svg","size":152975},{"name":"iphone-hand.svg","path":"static/assets/img/iphone-hand.svg","size":9802},{"name":"joomla1.webp","path":"static/assets/img/joomla1.webp","size":44546},{"name":"kaleidico-26MJGnCM0Wc-unsplash.jpg","path":"static/assets/img/kaleidico-26MJGnCM0Wc-unsplash.jpg","size":1423975},{"name":"logo-design-services.png","path":"static/assets/img/logo-design-services.png","size":12772},{"name":"magento1.webp","path":"static/assets/img/magento1.webp","size":10626},{"name":"magento2.webp","path":"static/assets/img/magento2.webp","size":6614},{"name":"markus-spiske-xekxE_VR0Ec-unsplash.jpg","path":"static/assets/img/markus-spiske-xekxE_VR0Ec-unsplash.jpg","size":3043440},{"name":"mobile.webp","path":"static/assets/img/mobile.webp","size":15906},{"name":"mobile2.webp","path":"static/assets/img/mobile2.webp","size":21374},{"name":"offshore.webp","path":"static/assets/img/offshore.webp","size":51192},{"name":"peps.png","path":"static/assets/img/peps.png","size":172889},{"name":"print-design-services.png","path":"static/assets/img/print-design-services.png","size":10346},{"name":"product-features.png","path":"static/assets/img/product-features.png","size":9581},{"name":"product-screen-1.png","path":"static/assets/img/product-screen-1.png","size":14524},{"name":"react-js.webp","path":"static/assets/img/react-js.webp","size":8430},{"name":"responsive-64.png","path":"static/assets/img/responsive-64.png","size":583},{"name":"scrum.svg","path":"static/assets/img/scrum.svg","size":69634},{"name":"services.png","path":"static/assets/img/services.png","size":60628},{"name":"simple-iphone.svg","path":"static/assets/img/simple-iphone.svg","size":3383},{"name":"tabs.svg","path":"static/assets/img/tabs.svg","size":14561},{"name":"team-1.jpg","path":"static/assets/img/team/team-1.jpg","size":40201},{"name":"team-2.jpg","path":"static/assets/img/team/team-2.jpg","size":49059},{"name":"team-3.jpg","path":"static/assets/img/team/team-3.jpg","size":36680},{"name":"team-4.jpg","path":"static/assets/img/team/team-4.jpg","size":27423},{"name":"testimonials-1.jpg","path":"static/assets/img/testimonials/testimonials-1.jpg","size":39727},{"name":"testimonials-2.jpg","path":"static/assets/img/testimonials/testimonials-2.jpg","size":57584},{"name":"testimonials-3.jpg","path":"static/assets/img/testimonials/testimonials-3.jpg","size":17247},{"name":"testimonials-4.jpg","path":"static/assets/img/testimonials/testimonials-4.jpg","size":20220},{"name":"testimonials-5.jpg","path":"static/assets/img/testimonials/testimonials-5.jpg","size":22595},{"name":"what-people-like.png","path":"static/assets/img/what-people-like.png","size":43077},{"name":"wordpress-development.webp","path":"static/assets/img/wordpress-development.webp","size":3414},{"name":"wordpress-development1.webp","path":"static/assets/img/wordpress-development1.webp","size":18820},{"name":"wordpress-plugins.webp","path":"static/assets/img/wordpress-plugins.webp","size":5564},{"name":"main.js","path":"static/assets/js/main.js","size":5514},{"name":"aos.css","path":"static/assets/vendor/aos/aos.css","size":26053},{"name":"aos.js","path":"static/assets/vendor/aos/aos.js","size":14690},{"name":"bootstrap-grid.css","path":"static/assets/vendor/bootstrap/css/bootstrap-grid.css","size":67472},{"name":"bootstrap-grid.css.map","path":"static/assets/vendor/bootstrap/css/bootstrap-grid.css.map","size":157643},{"name":"bootstrap-grid.min.css","path":"static/assets/vendor/bootstrap/css/bootstrap-grid.min.css","size":50636},{"name":"bootstrap-grid.min.css.map","path":"static/assets/vendor/bootstrap/css/bootstrap-grid.min.css.map","size":115006},{"name":"bootstrap-reboot.css","path":"static/assets/vendor/bootstrap/css/bootstrap-reboot.css","size":4800},{"name":"bootstrap-reboot.css.map","path":"static/assets/vendor/bootstrap/css/bootstrap-reboot.css.map","size":77215},{"name":"bootstrap-reboot.min.css","path":"static/assets/vendor/bootstrap/css/bootstrap-reboot.min.css","size":3935},{"name":"bootstrap-reboot.min.css.map","path":"static/assets/vendor/bootstrap/css/bootstrap-reboot.min.css.map","size":32551},{"name":"bootstrap.css","path":"static/assets/vendor/bootstrap/css/bootstrap.css","size":198240},{"name":"bootstrap.css.map","path":"static/assets/vendor/bootstrap/css/bootstrap.css.map","size":508537},{"name":"bootstrap.min.css","path":"static/assets/vendor/bootstrap/css/bootstrap.min.css","size":160392},{"name":"bootstrap.min.css.map","path":"static/assets/vendor/bootstrap/css/bootstrap.min.css.map","size":646986},{"name":"bootstrap.bundle.js","path":"static/assets/vendor/bootstrap/js/bootstrap.bundle.js","size":236517},{"name":"bootstrap.bundle.js.map","path":"static/assets/vendor/bootstrap/js/bootstrap.bundle.js.map","size":408140},{"name":"bootstrap.bundle.min.js","path":"static/assets/vendor/bootstrap/js/bootstrap.bundle.min.js","size":84152},{"name":"bootstrap.bundle.min.js.map","path":"static/assets/vendor/bootstrap/js/bootstrap.bundle.min.js.map","size":315680},{"name":"bootstrap.js","path":"static/assets/vendor/bootstrap/js/bootstrap.js","size":143686},{"name":"bootstrap.js.map","path":"static/assets/vendor/bootstrap/js/bootstrap.js.map","size":253028},{"name":"bootstrap.min.js","path":"static/assets/vendor/bootstrap/js/bootstrap.min.js","size":63240},{"name":"bootstrap.min.js.map","path":"static/assets/vendor/bootstrap/js/bootstrap.min.js.map","size":191971},{"name":"animations.css","path":"static/assets/vendor/boxicons/css/animations.css","size":7137},{"name":"boxicons.css","path":"static/assets/vendor/boxicons/css/boxicons.css","size":87141},{"name":"boxicons.min.css","path":"static/assets/vendor/boxicons/css/boxicons.min.css","size":63235},{"name":"transformations.css","path":"static/assets/vendor/boxicons/css/transformations.css","size":653},{"name":"boxicons.eot","path":"static/assets/vendor/boxicons/fonts/boxicons.eot","size":273536},{"name":"boxicons.svg","path":"static/assets/vendor/boxicons/fonts/boxicons.svg","size":975365},{"name":"boxicons.ttf","path":"static/assets/vendor/boxicons/fonts/boxicons.ttf","size":273368},{"name":"boxicons.woff","path":"static/assets/vendor/boxicons/fonts/boxicons.woff","size":273444},{"name":"boxicons.woff2","path":"static/assets/vendor/boxicons/fonts/boxicons.woff2","size":93260},{"name":"counterup.min.js","path":"static/assets/vendor/counterup/counterup.min.js","size":2406},{"name":"icofont.woff","path":"static/assets/vendor/icofont/fonts/icofont.woff","size":645604},{"name":"icofont.woff2","path":"static/assets/vendor/icofont/fonts/icofont.woff2","size":537868},{"name":"icofont.min.css","path":"static/assets/vendor/icofont/icofont.min.css","size":92208},{"name":"jquery.min.js","path":"static/assets/vendor/jquery/jquery.min.js","size":89476},{"name":"jquery.min.map","path":"static/assets/vendor/jquery/jquery.min.map","size":137974},{"name":"jquery.easing.min.js","path":"static/assets/vendor/jquery.easing/jquery.easing.min.js","size":2532},{"name":"LICENSE","path":"static/assets/vendor/owl.carousel/LICENSE","size":1095},{"name":"README.md","path":"static/assets/vendor/owl.carousel/README.md","size":3979},{"name":"ajax-loader.gif","path":"static/assets/vendor/owl.carousel/assets/ajax-loader.gif","size":3208},{"name":"owl.carousel.css","path":"static/assets/vendor/owl.carousel/assets/owl.carousel.css","size":4744},{"name":"owl.carousel.min.css","path":"static/assets/vendor/owl.carousel/assets/owl.carousel.min.css","size":3351},{"name":"owl.theme.default.css","path":"static/assets/vendor/owl.carousel/assets/owl.theme.default.css","size":1380},{"name":"owl.theme.default.min.css","path":"static/assets/vendor/owl.carousel/assets/owl.theme.default.min.css","size":1013},{"name":"owl.theme.green.css","path":"static/assets/vendor/owl.carousel/assets/owl.theme.green.css","size":1378},{"name":"owl.theme.green.min.css","path":"static/assets/vendor/owl.carousel/assets/owl.theme.green.min.css","size":1013},{"name":"owl.video.play.png","path":"static/assets/vendor/owl.carousel/assets/owl.video.play.png","size":4976},{"name":"owl.carousel.js","path":"static/assets/vendor/owl.carousel/owl.carousel.js","size":89992},{"name":"owl.carousel.min.js","path":"static/assets/vendor/owl.carousel/owl.carousel.min.js","size":44342},{"name":"validate.js","path":"static/assets/vendor/php-email-form/validate.js","size":3537},{"name":"remixicon.css","path":"static/assets/vendor/remixicon/remixicon.css","size":110438},{"name":"remixicon.eot","path":"static/assets/vendor/remixicon/remixicon.eot","size":403228},{"name":"remixicon.less","path":"static/assets/vendor/remixicon/remixicon.less","size":110450},{"name":"remixicon.svg","path":"static/assets/vendor/remixicon/remixicon.svg","size":1195522},{"name":"remixicon.symbol.svg","path":"static/assets/vendor/remixicon/remixicon.symbol.svg","size":897931},{"name":"remixicon.ttf","path":"static/assets/vendor/remixicon/remixicon.ttf","size":403056},{"name":"remixicon.woff","path":"static/assets/vendor/remixicon/remixicon.woff","size":172876},{"name":"remixicon.woff2","path":"static/assets/vendor/remixicon/remixicon.woff2","size":125268},{"name":"venobox.css","path":"static/assets/vendor/venobox/venobox.css","size":20309},{"name":"venobox.js","path":"static/assets/vendor/venobox/venobox.js","size":37668},{"name":"venobox.min.css","path":"static/assets/vendor/venobox/venobox.min.css","size":18726},{"name":"venobox.min.js","path":"static/assets/vendor/venobox/venobox.min.js","size":15013},{"name":"jquery.waypoints.min.js","path":"static/assets/vendor/waypoints/jquery.waypoints.min.js","size":9028},{"name":"_base.html","path":"templates/_base.html","size":18647},{"name":"about.html","path":"templates/about.html","size":10543},{"name":"email_confirmation_message.txt","path":"templates/account/email/email_confirmation_message.txt","size":566},{"name":"email_confirmation_subject.txt","path":"templates/account/email/email_confirmation_subject.txt","size":129},{"name":"email_confirm.html","path":"templates/account/email_confirm.html","size":1046},{"name":"login.html","path":"templates/account/login.html","size":1116},{"name":"logout.html","path":"templates/account/logout.html","size":800},{"name":"password_change.html","path":"templates/account/password_change.html","size":1074},{"name":"password_reset.html","path":"templates/account/password_reset.html","size":1344},{"name":"password_reset_done.html","path":"templates/account/password_reset_done.html","size":898},{"name":"password_reset_from_key.html","path":"templates/account/password_reset_from_key.html","size":1638},{"name":"password_reset_from_key_done.html","path":"templates/account/password_reset_from_key_done.html","size":643},{"name":"signup.html","path":"templates/account/signup.html","size":885},{"name":"angularjs_dev.html","path":"templates/angularjs_dev.html","size":9080},{"name":"edit_post.html","path":"templates/blog/edit_post.html","size":1141},{"name":"new_post.html","path":"templates/blog/new_post.html","size":1141},{"name":"post_delete.html","path":"templates/blog/post_delete.html","size":306},{"name":"post_detail.html","path":"templates/blog/post_detail.html","size":7094},{"name":"post_list.html","path":"templates/blog/post_list.html","size":4279},{"name":"recent_posts.html","path":"templates/blog/recent_posts.html","size":243},{"name":"search_results.html","path":"templates/blog/search_results.html","size":3960},{"name":"drupal_dev.html","path":"templates/drupal_dev.html","size":9363},{"name":"form_base.html","path":"templates/form_base.html","size":9638},{"name":"graphics_dev.html","path":"templates/graphics_dev.html","size":12100},{"name":"hire_drupal_dev.html","path":"templates/hire_drupal_dev.html","size":11748},{"name":"hire_joomla_dev.html","path":"templates/hire_joomla_dev.html","size":11374},{"name":"hire_laravel_dev.html","path":"templates/hire_laravel_dev.html","size":11886},{"name":"hire_php_dev.html","path":"templates/hire_php_dev.html","size":14641},{"name":"hire_web_dev.html","path":"templates/hire_web_dev.html","size":13337},{"name":"hire_wordpress_dev.html","path":"templates/hire_wordpress_dev.html","size":12122},{"name":"home.html","path":"templates/home.html","size":6115},{"name":"html5_dev.html","path":"templates/html5_dev.html","size":6238},{"name":"joomla_dev.html","path":"templates/joomla_dev.html","size":8935},{"name":"laravel_dev.html","path":"templates/laravel_dev.html","size":9254},{"name":"login_base.html","path":"templates/login_base.html","size":1239},{"name":"magento_dev.html","path":"templates/magento_dev.html","size":8662},{"name":"messages.html","path":"templates/messages.html","size":282},{"name":"mobile_dev.html","path":"templates/mobile_dev.html","size":12759},{"name":"offshore_sw_dev.html","path":"templates/offshore_sw_dev.html","size":12860},{"name":"php_dev.html","path":"templates/php_dev.html","size":10177},{"name":"python_dev.html","path":"templates/python_dev.html","size":8978},{"name":"quote.html","path":"templates/quote.html","size":2886},{"name":"reactjs_dev.html","path":"templates/reactjs_dev.html","size":9459},{"name":"software_dev.html","path":"templates/software_dev.html","size":13131},{"name":"web_dev.html","path":"templates/web_dev.html","size":12756},{"name":"wordpress_dev.html","path":"templates/wordpress_dev.html","size":11071},{"name":"todo.txt","path":"todo.txt","size":129},{"name":"__init__.py","path":"users/__init__.py","size":0},{"name":"admin.py","path":"users/admin.py","size":529},{"name":"apps.py","path":"users/apps.py","size":85},{"name":"forms.py","path":"users/forms.py","size":655},{"name":"0001_initial.py","path":"users/migrations/0001_initial.py","size":2876},{"name":"0002_profile.py","path":"users/migrations/0002_profile.py","size":757},{"name":"__init__.py","path":"users/migrations/__init__.py","size":0},{"name":"models.py","path":"users/models.py","size":703},{"name":"tests.py","path":"users/tests.py","size":1857},{"name":"urls.py","path":"users/urls.py","size":164},{"name":"views.py","path":"users/views.py","size":510}]